[{"tags": ["mysql", "server", "dart", "sqljocky"], "comments": [{"owner": {"reputation": 483716, "user_id": 217408, "user_type": "registered", "accept_rate": 97, "profile_image": "https://i.stack.imgur.com/IlnZm.jpg?s=128&g=1", "display_name": "G&#252;nter Z&#246;chbauer", "link": "https://stackoverflow.com/users/217408/g%c3%bcnter-z%c3%b6chbauer"}, "edited": false, "score": 0, "creation_date": 1491985807, "post_id": 43364181, "comment_id": 73790127, "body": "What do you get when you add <code>print(results);</code> before <code>results.forEach(...)</code>?"}, {"owner": {"reputation": 4197, "user_id": 7190575, "user_type": "registered", "accept_rate": 77, "profile_image": "https://www.gravatar.com/avatar/63b85f6a33e1b032dabc877b7ff4af50?s=128&d=identicon&r=PG&f=1", "display_name": "OhMad", "link": "https://stackoverflow.com/users/7190575/ohmad"}, "reply_to_user": {"reputation": 483716, "user_id": 217408, "user_type": "registered", "accept_rate": 97, "profile_image": "https://i.stack.imgur.com/IlnZm.jpg?s=128&g=1", "display_name": "G&#252;nter Z&#246;chbauer", "link": "https://stackoverflow.com/users/217408/g%c3%bcnter-z%c3%b6chbauer"}, "edited": false, "score": 0, "creation_date": 1491986384, "post_id": 43364181, "comment_id": 73790535, "body": "Nothing. it just doesn&#39;t print."}, {"owner": {"reputation": 483716, "user_id": 217408, "user_type": "registered", "accept_rate": 97, "profile_image": "https://i.stack.imgur.com/IlnZm.jpg?s=128&g=1", "display_name": "G&#252;nter Z&#246;chbauer", "link": "https://stackoverflow.com/users/217408/g%c3%bcnter-z%c3%b6chbauer"}, "edited": false, "score": 0, "creation_date": 1491986697, "post_id": 43364181, "comment_id": 73790755, "body": "I don&#39;t think it&#39;s related to your code. Sounds more like the database doesn&#39;t respond. Do you get anything different when you change the query to <code>pool.query(&quot;select * from discussions limit 10&quot;);</code> or <code>pool.query(&quot;select &#39;hello world&#39;&quot;);</code>?"}, {"owner": {"reputation": 4197, "user_id": 7190575, "user_type": "registered", "accept_rate": 77, "profile_image": "https://www.gravatar.com/avatar/63b85f6a33e1b032dabc877b7ff4af50?s=128&d=identicon&r=PG&f=1", "display_name": "OhMad", "link": "https://stackoverflow.com/users/7190575/ohmad"}, "reply_to_user": {"reputation": 483716, "user_id": 217408, "user_type": "registered", "accept_rate": 97, "profile_image": "https://i.stack.imgur.com/IlnZm.jpg?s=128&g=1", "display_name": "G&#252;nter Z&#246;chbauer", "link": "https://stackoverflow.com/users/217408/g%c3%bcnter-z%c3%b6chbauer"}, "edited": false, "score": 0, "creation_date": 1491987138, "post_id": 43364181, "comment_id": 73791076, "body": "No, nothing at all. My mysql client is running, tho."}, {"owner": {"reputation": 483716, "user_id": 217408, "user_type": "registered", "accept_rate": 97, "profile_image": "https://i.stack.imgur.com/IlnZm.jpg?s=128&g=1", "display_name": "G&#252;nter Z&#246;chbauer", "link": "https://stackoverflow.com/users/217408/g%c3%bcnter-z%c3%b6chbauer"}, "edited": false, "score": 0, "creation_date": 1491987311, "post_id": 43364181, "comment_id": 73791231, "body": "That&#39;s weird. Sorry, out of ideas."}, {"owner": {"reputation": 4197, "user_id": 7190575, "user_type": "registered", "accept_rate": 77, "profile_image": "https://www.gravatar.com/avatar/63b85f6a33e1b032dabc877b7ff4af50?s=128&d=identicon&r=PG&f=1", "display_name": "OhMad", "link": "https://stackoverflow.com/users/7190575/ohmad"}, "reply_to_user": {"reputation": 483716, "user_id": 217408, "user_type": "registered", "accept_rate": 97, "profile_image": "https://i.stack.imgur.com/IlnZm.jpg?s=128&g=1", "display_name": "G&#252;nter Z&#246;chbauer", "link": "https://stackoverflow.com/users/217408/g%c3%bcnter-z%c3%b6chbauer"}, "edited": false, "score": 1, "creation_date": 1491987858, "post_id": 43364181, "comment_id": 73791659, "body": "Yep, same :D Going to figure it out, I&#39;ll let you know if I do."}, {"owner": {"reputation": 4197, "user_id": 7190575, "user_type": "registered", "accept_rate": 77, "profile_image": "https://www.gravatar.com/avatar/63b85f6a33e1b032dabc877b7ff4af50?s=128&d=identicon&r=PG&f=1", "display_name": "OhMad", "link": "https://stackoverflow.com/users/7190575/ohmad"}, "reply_to_user": {"reputation": 483716, "user_id": 217408, "user_type": "registered", "accept_rate": 97, "profile_image": "https://i.stack.imgur.com/IlnZm.jpg?s=128&g=1", "display_name": "G&#252;nter Z&#246;chbauer", "link": "https://stackoverflow.com/users/217408/g%c3%bcnter-z%c3%b6chbauer"}, "edited": false, "score": 0, "creation_date": 1491988294, "post_id": 43364181, "comment_id": 73792032, "body": "Oh wow, it was my dumb mistake. It wanted only the port of mysql, which is 3306 by default. Huh, in Laravel 1234 worked just fine for the database credentials... ^^"}, {"owner": {"reputation": 483716, "user_id": 217408, "user_type": "registered", "accept_rate": 97, "profile_image": "https://i.stack.imgur.com/IlnZm.jpg?s=128&g=1", "display_name": "G&#252;nter Z&#246;chbauer", "link": "https://stackoverflow.com/users/217408/g%c3%bcnter-z%c3%b6chbauer"}, "edited": false, "score": 0, "creation_date": 1491988634, "post_id": 43364181, "comment_id": 73792269, "body": "Weird that you didn&#39;t get an error."}, {"owner": {"reputation": 1868, "user_id": 1416886, "user_type": "registered", "accept_rate": 100, "profile_image": "https://www.gravatar.com/avatar/b1816b2eac989b20642bb419e3b51605?s=128&d=identicon&r=PG", "display_name": "filiph", "link": "https://stackoverflow.com/users/1416886/filiph"}, "edited": false, "score": 0, "creation_date": 1493423763, "post_id": 43364181, "comment_id": 74426939, "body": "Great to see you solved the issue. Just for SO hygiene, could you please put your answer-in-comment into a proper answer, and then mark this question answered? Also, it <i>is</i> weird that the query didn&#39;t throw an error and hasn&#39;t timed out. Could you file an issue to sqljocky?"}], "answers": [{"tags": [], "owner": {"reputation": 4197, "user_id": 7190575, "user_type": "registered", "accept_rate": 77, "profile_image": "https://www.gravatar.com/avatar/63b85f6a33e1b032dabc877b7ff4af50?s=128&d=identicon&r=PG&f=1", "display_name": "OhMad", "link": "https://stackoverflow.com/users/7190575/ohmad"}, "is_accepted": false, "score": 1, "last_activity_date": 1493448102, "creation_date": 1493448102, "answer_id": 43692624, "question_id": 43364181, "link": "https://stackoverflow.com/questions/43364181/dart-sqljocky-no-response-from-the-database/43692624#43692624", "title": "Dart SqlJocky - No response from the database", "body": "<p>The problem I had was that I was refering to the port of my localhost, and not to the port of MySql only. Entering 3306 as the port worked for me.</p>\n"}], "owner": {"reputation": 4197, "user_id": 7190575, "user_type": "registered", "accept_rate": 77, "profile_image": "https://www.gravatar.com/avatar/63b85f6a33e1b032dabc877b7ff4af50?s=128&d=identicon&r=PG&f=1", "display_name": "OhMad", "link": "https://stackoverflow.com/users/7190575/ohmad"}, "delete_vote_count": 0, "reopen_vote_count": 0, "close_vote_count": 0, "is_answered": true, "view_count": 114, "favorite_count": 0, "answer_count": 1, "score": 0, "last_activity_date": 1493448102, "creation_date": 1491985535, "question_id": 43364181, "link": "https://stackoverflow.com/questions/43364181/dart-sqljocky-no-response-from-the-database", "title": "Dart SqlJocky - No response from the database", "body": "<p>I am currently trying to setup a database connection between my server (command line server) and my localhost xampp mysql. this is running in my main function:</p>\n\n<pre><code>main() async {\n  var pool = new ConnectionPool(\n    host: 'localhost', port: 1234,\n    user: 'root', password: 'password',\n    db: 'angularsite', max: 5);\n\n  var results = await pool.query(\"select * from discussions\");\n\n  results.forEach((row) {\n    print('Row: ${row}');\n  });\n}\n</code></pre>\n\n<p>As you can see, it's basically the example that sqljocky provides. I just replaced the credentials with mine. I don't get an error message, nothing happens. From using the good old print method I know that the execution of the code doesn't go beyond the \"pool.query\" line. (The ConnectionPool does indeed instanciate)</p>\n\n<p>Anything I did wrong?</p>\n\n<p>Thanks in advance</p>\n"}, {"tags": ["angular", "dart", "angular-material", "angular2-dart", "dart-angular-templates"], "answers": [{"tags": [], "owner": {"reputation": 483716, "user_id": 217408, "user_type": "registered", "accept_rate": 97, "profile_image": "https://i.stack.imgur.com/IlnZm.jpg?s=128&g=1", "display_name": "G&#252;nter Z&#246;chbauer", "link": "https://stackoverflow.com/users/217408/g%c3%bcnter-z%c3%b6chbauer"}, "is_accepted": true, "score": 2, "last_activity_date": 1491930899, "creation_date": 1491930899, "answer_id": 43352330, "question_id": 43352011, "link": "https://stackoverflow.com/questions/43352011/angular-dart-and-material-inputs-how-to-put-a-link-into-a-checkbox-label/43352330#43352330", "title": "Angular / Dart and Material Inputs: How to put a link into a checkbox label?", "body": "<p>HTML in string interpolation bindings is not supported.\nThe <code>label</code> attribute is added using string interpolation</p>\n\n<pre><code>&lt;div class=\"content\"&gt;\n  {{label}}\n  &lt;ng-content&gt;&lt;/ng-content&gt;\n&lt;/div&gt;\n</code></pre>\n\n<p><a href=\"https://github.com/dart-lang/angular2_components/blob/dedd4cb56dc931b76c282daa3c8f78856cb7e8ad/lib/src/components/material_checkbox/material_checkbox.html#L19-L22\" rel=\"nofollow noreferrer\">material-checkbox template source</a></p>\n\n<p>As you see in the template, projected context is supported though, therefore this should do what you want:</p>\n\n<pre><code>&lt;material-checkbox [(ngModel)]=\"agbsAccepted\"&gt;\n  I have read &lt;a href=\"/#/terms\" target=\"_blank\"&gt;the terms and conditions&lt;/a&gt; and accept those.\n&lt;/material-checkbox&gt;\n</code></pre>\n"}], "owner": {"reputation": 11950, "user_id": 576746, "user_type": "registered", "accept_rate": 83, "profile_image": "https://www.gravatar.com/avatar/fd655b00d23f25a744dbd630b7fdd09d?s=128&d=identicon&r=PG", "display_name": "Blackbam", "link": "https://stackoverflow.com/users/576746/blackbam"}, "delete_vote_count": 0, "reopen_vote_count": 0, "close_vote_count": 0, "is_answered": true, "view_count": 542, "favorite_count": 0, "accepted_answer_id": 43352330, "answer_count": 1, "score": 2, "last_activity_date": 1491930899, "creation_date": 1491929773, "question_id": 43352011, "link": "https://stackoverflow.com/questions/43352011/angular-dart-and-material-inputs-how-to-put-a-link-into-a-checkbox-label", "title": "Angular / Dart and Material Inputs: How to put a link into a checkbox label?", "body": "<p>Simple question: Is this somehow possible?</p>\n\n<pre><code>&lt;material-checkbox [(ngModel)]=\"agbsAccepted\" label='I have read &lt;a href=\"/#/terms\" target=\"_blank\"&gt;the terms and conditions&lt;/a&gt; and accept those.'&gt;&lt;/material-checkbox&gt;\n</code></pre>\n\n<p>If I write it like this the HTML is parsed into a normal string. But if I write it do not use the label property its sometimes difficult to style.</p>\n"}, {"tags": ["dart", "flutter"], "answers": [{"tags": [], "owner": {"reputation": 5420, "user_id": 6414732, "user_type": "registered", "accept_rate": 80, "profile_image": "https://i.stack.imgur.com/pBmXr.png?s=128&g=1", "display_name": "Rainer Wittmann", "link": "https://stackoverflow.com/users/6414732/rainer-wittmann"}, "is_accepted": false, "score": 0, "last_activity_date": 1491923987, "creation_date": 1491923987, "answer_id": 43350033, "question_id": 43349013, "link": "https://stackoverflow.com/questions/43349013/how-to-open-a-popupmenubutton/43350033#43350033", "title": "How to open a PopupMenuButton?", "body": "<p>I don't think there is a way to achieve this behaviour. Although you can attach an <code>onTap</code> attribute to the tile, you can't access the MenuButton from the 'outside'  </p>\n\n<p>An approach you could take is to use <a href=\"https://docs.flutter.io/flutter/material/ExpansionPanel-class.html\" rel=\"nofollow noreferrer\">ExpansionPanels</a> because they look like ListTiles and are intended to allow easy modification and editing.  </p>\n"}, {"comments": [{"owner": {"reputation": 366, "user_id": 1670305, "user_type": "registered", "profile_image": "https://www.gravatar.com/avatar/417e1e15a4a45757a985156d5c860064?s=128&d=identicon&r=PG", "display_name": "Srini", "link": "https://stackoverflow.com/users/1670305/srini"}, "edited": false, "score": 0, "creation_date": 1551335947, "post_id": 43365377, "comment_id": 96604900, "body": "use the offset property to position it differently"}, {"owner": {"reputation": 1874, "user_id": 10329023, "user_type": "registered", "profile_image": "https://i.stack.imgur.com/cnuxe.jpg?s=128&g=1", "display_name": "Kamlesh", "link": "https://stackoverflow.com/users/10329023/kamlesh"}, "edited": false, "score": 0, "creation_date": 1614578778, "post_id": 43365377, "comment_id": 117417903, "body": "How to use multi-level PopupMenuItems?"}], "tags": [], "owner": {"reputation": 5420, "user_id": 6414732, "user_type": "registered", "accept_rate": 80, "profile_image": "https://i.stack.imgur.com/pBmXr.png?s=128&g=1", "display_name": "Rainer Wittmann", "link": "https://stackoverflow.com/users/6414732/rainer-wittmann"}, "is_accepted": false, "score": 6, "last_activity_date": 1491988808, "creation_date": 1491988808, "answer_id": 43365377, "question_id": 43349013, "link": "https://stackoverflow.com/questions/43349013/how-to-open-a-popupmenubutton/43365377#43365377", "title": "How to open a PopupMenuButton?", "body": "<p>I found a solution to your question. You can provide a child to PopupMenuButton which can be any Widget including a ListTile (see code below). Only problem is that the PopupMenu opens on the left side of the ListTile.</p>\n\n<pre><code>final popupMenu = new PopupMenuButton(\n  child: new ListTile(\n    title: new Text('Doge or lion?'),\n    trailing: const Icon(Icons.more_vert),\n  ),\n  itemBuilder: (_) =&gt; &lt;PopupMenuItem&lt;String&gt;&gt;[\n            new PopupMenuItem&lt;String&gt;(\n                child: new Text('Doge'), value: 'Doge'),\n            new PopupMenuItem&lt;String&gt;(\n                child: new Text('Lion'), value: 'Lion'),\n          ],\n  onSelected: _doSomething,\n)\n</code></pre>\n"}, {"comments": [{"owner": {"reputation": 1793, "user_id": 7851337, "user_type": "registered", "accept_rate": 45, "profile_image": "https://i.stack.imgur.com/oMgO3.jpg?s=128&g=1", "display_name": "DogeLion", "link": "https://stackoverflow.com/users/7851337/dogelion"}, "edited": false, "score": 0, "creation_date": 1492069346, "post_id": 43383966, "comment_id": 73834029, "body": "Thank you Eric! Yeah, the widgets described in those github issues are something that I was looking for."}, {"owner": {"reputation": 1275, "user_id": 4574188, "user_type": "registered", "accept_rate": 60, "profile_image": "https://graph.facebook.com/565076226962422/picture?type=large", "display_name": "Ajay Kumar", "link": "https://stackoverflow.com/users/4574188/ajay-kumar"}, "edited": false, "score": 0, "creation_date": 1585823384, "post_id": 43383966, "comment_id": 107900712, "body": "Thanks  I used this solution"}], "tags": [], "owner": {"reputation": 2523, "user_id": 6669611, "user_type": "registered", "profile_image": "https://lh6.googleusercontent.com/-r4OJyp3Hp-8/AAAAAAAAAAI/AAAAAAAAAvI/gqRexRhkGoU/photo.jpg?sz=128", "display_name": "Eric Seidel", "link": "https://stackoverflow.com/users/6669611/eric-seidel"}, "is_accepted": true, "score": 29, "last_activity_date": 1492569210, "last_edit_date": 1492569210, "creation_date": 1492060291, "answer_id": 43383966, "question_id": 43349013, "link": "https://stackoverflow.com/questions/43349013/how-to-open-a-popupmenubutton/43383966#43383966", "title": "How to open a PopupMenuButton?", "body": "<p>This works, but is inelegant (and has the same display problem as Rainer's solution above:</p>\n\n<pre><code>class _MyHomePageState extends State&lt;MyHomePage&gt; {\n  final GlobalKey _menuKey = new GlobalKey();\n\n  @override\n  Widget build(BuildContext context) {\n    final button = new PopupMenuButton(\n        key: _menuKey,\n        itemBuilder: (_) =&gt; &lt;PopupMenuItem&lt;String&gt;&gt;[\n              new PopupMenuItem&lt;String&gt;(\n                  child: const Text('Doge'), value: 'Doge'),\n              new PopupMenuItem&lt;String&gt;(\n                  child: const Text('Lion'), value: 'Lion'),\n            ],\n        onSelected: (_) {});\n\n    final tile =\n        new ListTile(title: new Text('Doge or lion?'), trailing: button, onTap: () {\n          // This is a hack because _PopupMenuButtonState is private.\n          dynamic state = _menuKey.currentState;\n          state.showButtonMenu();\n        });\n    return new Scaffold(\n      body: new Center(\n        child: tile,\n      ),\n    );\n  }\n}\n</code></pre>\n\n<p>I suspect what you're actually asking for is something like what is tracked by <a href=\"https://github.com/flutter/flutter/issues/254\" rel=\"noreferrer\">https://github.com/flutter/flutter/issues/254</a> or <a href=\"https://github.com/flutter/flutter/issues/8277\" rel=\"noreferrer\">https://github.com/flutter/flutter/issues/8277</a> -- the ability to associated a label with a control and have the label be clickable -- and is a missing feature from the Flutter framework.</p>\n"}, {"comments": [{"owner": {"reputation": 461, "user_id": 10841432, "user_type": "registered", "profile_image": "https://www.gravatar.com/avatar/d737f8129e54c4b2ab5568efd1f082c7?s=128&d=identicon&r=PG&f=1", "display_name": "Texv", "link": "https://stackoverflow.com/users/10841432/texv"}, "edited": false, "score": 2, "creation_date": 1601167827, "post_id": 59695326, "comment_id": 113321292, "body": "How can I use the onSelected property from the PopUpMenuButton into your method? Lets say for example, if value Doge is selected, I want to navigate to Doge.dart page"}, {"owner": {"reputation": 881, "user_id": 6901192, "user_type": "registered", "profile_image": "https://i.stack.imgur.com/6JxNi.jpg?s=128&g=1", "display_name": "Ahmed Nour Jamal El-Din", "link": "https://stackoverflow.com/users/6901192/ahmed-nour-jamal-el-din"}, "edited": false, "score": 2, "creation_date": 1602085588, "post_id": 59695326, "comment_id": 113610386, "body": "Perfect answer, I just had to replace 0 by other values: <code>RelativeRect.fromLTRB(left, top, left+1, top+1),</code>"}], "tags": [], "owner": {"reputation": 597, "user_id": 5557585, "user_type": "registered", "profile_image": "https://lh3.googleusercontent.com/-HJ5faS1sHtQ/AAAAAAAAAAI/AAAAAAAAApY/PE3LfjNskuY/photo.jpg?sz=128", "display_name": "Vishal Singh", "link": "https://stackoverflow.com/users/5557585/vishal-singh"}, "is_accepted": false, "score": 15, "last_activity_date": 1578752929, "creation_date": 1578752929, "answer_id": 59695326, "question_id": 43349013, "link": "https://stackoverflow.com/questions/43349013/how-to-open-a-popupmenubutton/59695326#59695326", "title": "How to open a PopupMenuButton?", "body": "<p>I think it would be better do it in this way, rather than showing a PopupMenuButton</p>\n\n<pre><code>void _showPopupMenu() async {\n  await showMenu(\n    context: context,\n    position: RelativeRect.fromLTRB(100, 100, 100, 100),\n    items: [\n      PopupMenuItem&lt;String&gt;(\n          child: const Text('Doge'), value: 'Doge'),\n      PopupMenuItem&lt;String&gt;(\n          child: const Text('Lion'), value: 'Lion'),\n    ],\n    elevation: 8.0,\n  );\n}\n</code></pre>\n\n<hr>\n\n<p>There will be times when you would want to display <strong>_showPopupMenu</strong>     at the <strong>location where you pressed on the button</strong>\nUse GestureDetector for that</p>\n\n<pre><code>final tile = new ListTile(\n  title: new Text('Doge or lion?'),\n  trailing: GestureDetector(\n    onTapDown: (TapDownDetails details) {\n      _showPopupMenu(details.globalPosition);\n    },\n    child: Container(child: Text(\"Press Me\")),\n  ),\n);\n</code></pre>\n\n<p>and then _showPopupMenu will be like</p>\n\n<pre><code>_showPopupMenu(Offset offset) async {\n    double left = offset.dx;\n    double top = offset.dy;\n    await showMenu(\n    context: context,\n    position: RelativeRect.fromLTRB(left, top, 0, 0),\n    items: [\n      ...,\n    elevation: 8.0,\n  );\n}\n</code></pre>\n"}, {"tags": [], "owner": {"reputation": 11993, "user_id": 10563627, "user_type": "registered", "profile_image": "https://i.stack.imgur.com/xQL2O.jpg?s=128&g=1", "display_name": "Paresh Mangukiya", "link": "https://stackoverflow.com/users/10563627/paresh-mangukiya"}, "is_accepted": false, "score": 2, "last_activity_date": 1600419538, "creation_date": 1600419538, "answer_id": 63952566, "question_id": 43349013, "link": "https://stackoverflow.com/questions/43349013/how-to-open-a-popupmenubutton/63952566#63952566", "title": "How to open a PopupMenuButton?", "body": "<p>Use <a href=\"https://pub.dev/packages/popup_menu\" rel=\"nofollow noreferrer\">popup_menu</a> package as a library</p>\n<p>Add <code>popup_menu: ^1.0.5</code> in your <code>pubspec.yaml</code> dependencies. And import it:</p>\n<pre><code>import 'package:popup_menu/popup_menu.dart';\n</code></pre>\n<p>First, you should set the context at somewhere in you code. Like below:</p>\n<pre><code>PopupMenu.context = context;\n</code></pre>\n<p>Then create a <code>showPopup</code> widget and pass the required params:</p>\n<pre><code> void showPopup(Offset offset) {\n    PopupMenu menu = PopupMenu(\n        // backgroundColor: Colors.teal,\n        // lineColor: Colors.tealAccent,\n        maxColumn: 3,\n        items: [\n          MenuItem(title: 'Copy', image: Image.asset('assets/copy.png')),\n          MenuItem(title: 'Mail', image: Icon(Icons.mail, color: Colors.white)),\n          MenuItem(title: 'Power',image: Icon(Icons.power, color: Colors.white,)),\n        ],\n        onClickMenu: onClickMenu,\n        stateChanged: stateChanged,\n        onDismiss: onDismiss);\n    menu.show(rect: Rect.fromPoints(offset, offset));\n  }\n\n  void stateChanged(bool isShow) {\n    print('menu is ${isShow ? 'showing' : 'closed'}');\n  }\n\n  void onClickMenu(MenuItemProvider item) {\n    print('Click menu -&gt; ${item.menuTitle}');\n  }\n\n  void onDismiss() {\n    print('Menu is dismiss');\n  }\n</code></pre>\n<p>Here is the open popup</p>\n<pre><code>  @override\n  Widget build(BuildContext context) {\n\n  PopupMenu.context = context;  // This is the set context\n\n    return Scaffold(\n      appBar: AppBar(\n        title: Text('Show Popup')),\n      body: Stack(\n        children: &lt;Widget&gt;[\n          ListView.builder(\n            itemCount: list.length,\n            itemBuilder: (context, index) {\n             return MaterialButton(\n                child: GestureDetector(\n                  onTapUp: (TapUpDetails details) {\n                    showPopup(details.globalPosition);\n                  },\n                  child: ListTile(\n                    leading: IconButton(\n                      icon: Icon(Icons.restaurant_menu),\n                    ),\n                    title: Text(&quot;Select your categories&quot;),\n                    subtitle: Text(&quot;Sub Title&quot;),\n                    // onTap: showPopup,\n                  ),\n                ),\n\n              );\n            },\n          ),\n        ],\n      ),\n    );\n  }\n</code></pre>\n<p><a href=\"https://i.stack.imgur.com/DuLWI.gif\" rel=\"nofollow noreferrer\"><img src=\"https://i.stack.imgur.com/DuLWI.gif\" alt=\"enter image description here\" /></a></p>\n"}, {"tags": [], "owner": {"reputation": 103440, "user_id": 6618622, "user_type": "registered", "profile_image": "https://i.stack.imgur.com/Z7q0p.jpg?s=128&g=1", "display_name": "CopsOnRoad", "link": "https://stackoverflow.com/users/6618622/copsonroad"}, "is_accepted": false, "score": 0, "last_activity_date": 1609667850, "creation_date": 1609667850, "answer_id": 65548513, "question_id": 43349013, "link": "https://stackoverflow.com/questions/43349013/how-to-open-a-popupmenubutton/65548513#65548513", "title": "How to open a PopupMenuButton?", "body": "<p><strong>Screenshot:</strong></p>\n<p><a href=\"https://i.stack.imgur.com/hqreo.gif\" rel=\"nofollow noreferrer\"><img src=\"https://i.stack.imgur.com/hqreo.gif\" alt=\"enter image description here\" /></a></p>\n<hr />\n<p><strong>Full code:</strong></p>\n<pre class=\"lang-dart prettyprint-override\"><code>class MyPage extends StatelessWidget {\n  final GlobalKey&lt;PopupMenuButtonState&lt;int&gt;&gt; _key = GlobalKey();\n  @override\n  Widget build(BuildContext context) {\n    return Scaffold(\n      appBar: AppBar(\n        actions: [\n          PopupMenuButton&lt;int&gt;(\n            key: _key,\n            itemBuilder: (context) {\n              return &lt;PopupMenuEntry&lt;int&gt;&gt;[\n                PopupMenuItem(child: Text('0'), value: 0),\n                PopupMenuItem(child: Text('1'), value: 1),\n              ];\n            },\n          ),\n        ],\n      ),\n      body: RaisedButton(\n        onPressed: () =&gt; _key.currentState.showButtonMenu(),\n        child: Text('Open/Close menu'),\n      ),\n    );\n  }\n}\n</code></pre>\n"}], "owner": {"reputation": 1793, "user_id": 7851337, "user_type": "registered", "accept_rate": 45, "profile_image": "https://i.stack.imgur.com/oMgO3.jpg?s=128&g=1", "display_name": "DogeLion", "link": "https://stackoverflow.com/users/7851337/dogelion"}, "delete_vote_count": 0, "reopen_vote_count": 0, "close_vote_count": 0, "is_answered": true, "view_count": 32256, "favorite_count": 1, "accepted_answer_id": 43383966, "answer_count": 6, "score": 28, "last_activity_date": 1609667850, "creation_date": 1491921360, "last_edit_date": 1609666965, "question_id": 43349013, "link": "https://stackoverflow.com/questions/43349013/how-to-open-a-popupmenubutton", "title": "How to open a PopupMenuButton?", "body": "<p>How do I open a popup menu from a second widget?</p>\n\n<pre><code>final button = new PopupMenuButton(\n    itemBuilder: (_) =&gt; &lt;PopupMenuItem&lt;String&gt;&gt;[\n          new PopupMenuItem&lt;String&gt;(\n              child: const Text('Doge'), value: 'Doge'),\n          new PopupMenuItem&lt;String&gt;(\n              child: const Text('Lion'), value: 'Lion'),\n        ],\n    onSelected: _doSomething);\n\nfinal tile = new ListTile(title: new Text('Doge or lion?'), trailing: button);\n</code></pre>\n\n<p>I want to open the <code>button</code>'s menu by tapping on <code>tile</code>.</p>\n"}, {"tags": ["functional-programming", "dart"], "answers": [{"tags": [], "owner": {"reputation": 30488, "user_id": 22483, "user_type": "registered", "accept_rate": 50, "profile_image": "https://www.gravatar.com/avatar/b337d1e52bf3d796a7728def67a602fd?s=128&d=identicon&r=PG", "display_name": "Randal Schwartz", "link": "https://stackoverflow.com/users/22483/randal-schwartz"}, "is_accepted": false, "score": 6, "last_activity_date": 1491869899, "creation_date": 1491869899, "answer_id": 43334797, "question_id": 43334714, "link": "https://stackoverflow.com/questions/43334714/pass-a-typed-function-as-a-parameter-in-dart/43334797#43334797", "title": "Pass a typed function as a parameter in Dart", "body": "<p>This is what <a href=\"https://www.dartlang.org/guides/language/language-tour#typedefs\" rel=\"noreferrer\">typedefs</a> are for!</p>\n"}, {"tags": [], "owner": {"reputation": 3866, "user_id": 1340742, "user_type": "registered", "accept_rate": 83, "profile_image": "https://www.gravatar.com/avatar/df2fa6b1ea7372c21f48eb8a80939c31?s=128&d=identicon&r=PG", "display_name": "Richard Ambler", "link": "https://stackoverflow.com/users/1340742/richard-ambler"}, "is_accepted": false, "score": 15, "last_activity_date": 1535087236, "last_edit_date": 1535087236, "creation_date": 1491879420, "answer_id": 43336014, "question_id": 43334714, "link": "https://stackoverflow.com/questions/43334714/pass-a-typed-function-as-a-parameter-in-dart/43336014#43336014", "title": "Pass a typed function as a parameter in Dart", "body": "<p>Edit: Note that this answer contains outdated information. See <a href=\"https://stackoverflow.com/a/43611520/1340742\">Irn's answer</a> for more up-to-date information.</p>\n\n<p>Just to expand on Randal's answer, your code might look something like:</p>\n\n<pre><code>typedef void IntegerArgument(int x);\n\nvoid doSomething(IntegerArgument f) {\n    f(123);\n}\n</code></pre>\n\n<p><code>Function&lt;int&gt;</code> seems like it would be a nice idea but the problem is that we might want to specify return type as well as the type of an arbitrary number of arguments.</p>\n"}, {"tags": [], "owner": {"reputation": 483716, "user_id": 217408, "user_type": "registered", "accept_rate": 97, "profile_image": "https://i.stack.imgur.com/IlnZm.jpg?s=128&g=1", "display_name": "G&#252;nter Z&#246;chbauer", "link": "https://stackoverflow.com/users/217408/g%c3%bcnter-z%c3%b6chbauer"}, "is_accepted": false, "score": 4, "last_activity_date": 1491905019, "creation_date": 1491905019, "answer_id": 43342803, "question_id": 43334714, "link": "https://stackoverflow.com/questions/43334714/pass-a-typed-function-as-a-parameter-in-dart/43342803#43342803", "title": "Pass a typed function as a parameter in Dart", "body": "<p>You can have a function typed parameter or use a <code>typedef</code></p>\n\n<pre><code>void main() {\n  doSomething(xToString);\n  doSomething2(xToString);\n}\n\nString xToString(int s) =&gt; 's';\n\ntypedef String XToStringFn(int s);\n\nvoid doSomething(String f(int s)) {\n    print('value: ${f(123)}');\n}\n\nvoid doSomething2(XToStringFn f) {\n    print('value: ${f(123)}');\n}\n</code></pre>\n\n<p><a href=\"https://dartpad.dartlang.org/55631a373f7de0efbfb27d31ab6890e1\" rel=\"nofollow noreferrer\"><strong>DartPad example</strong></a></p>\n"}, {"comments": [{"owner": {"reputation": 3511, "user_id": 955422, "user_type": "registered", "accept_rate": 86, "profile_image": "https://i.stack.imgur.com/pJ3AT.png?s=128&g=1", "display_name": "Ikar Pohorsk&#253;", "link": "https://stackoverflow.com/users/955422/ikar-pohorsk%c3%bd"}, "edited": false, "score": 5, "creation_date": 1562068970, "post_id": 43611520, "comment_id": 100254064, "body": "This is great, thanks! Anyways, this answers only first half of the question. How about the return types?"}, {"owner": {"reputation": 35316, "user_id": 2156621, "user_type": "registered", "profile_image": "https://www.gravatar.com/avatar/83ed6aa5c7920063019e39f13f94c1b6?s=128&d=identicon&r=PG&f=1", "display_name": "lrn", "link": "https://stackoverflow.com/users/2156621/lrn"}, "reply_to_user": {"reputation": 3511, "user_id": 955422, "user_type": "registered", "accept_rate": 86, "profile_image": "https://i.stack.imgur.com/pJ3AT.png?s=128&g=1", "display_name": "Ikar Pohorsk&#253;", "link": "https://stackoverflow.com/users/955422/ikar-pohorsk%c3%bd"}, "edited": false, "score": 5, "creation_date": 1562075200, "post_id": 43611520, "comment_id": 100257903, "body": "Added example of a return type which is a function type."}, {"owner": {"reputation": 5021, "user_id": 4470135, "user_type": "registered", "accept_rate": 54, "profile_image": "https://i.stack.imgur.com/oXA6y.jpg?s=128&g=1", "display_name": "yuranos", "link": "https://stackoverflow.com/users/4470135/yuranos"}, "edited": false, "score": 0, "creation_date": 1562946981, "post_id": 43611520, "comment_id": 100553586, "body": "StreamSubscription&lt;T&gt; listen(void onData(T event),       {Function onError, void onDone(), bool cancelOnError}); - why are 2 different notations are used? What&#39;s the reason to use one or the other(onDone vs onError)? Maybe someone can add it to the answer?"}, {"owner": {"reputation": 35316, "user_id": 2156621, "user_type": "registered", "profile_image": "https://www.gravatar.com/avatar/83ed6aa5c7920063019e39f13f94c1b6?s=128&d=identicon&r=PG&f=1", "display_name": "lrn", "link": "https://stackoverflow.com/users/2156621/lrn"}, "edited": false, "score": 1, "creation_date": 1563135301, "post_id": 43611520, "comment_id": 100590540, "body": "The <code>onError</code> parameter is set to accept a <code>Function</code> (the super-type of all functions) rather than a specific function type. That&#39;s because it accepts both <code>void Function(Object)</code> and <code>void Function(Object, StackTrace)</code>, and there is no way to represent that type union in the Dart type system. The remaining parameters can be typed with the specific function type needed."}, {"owner": {"reputation": 987, "user_id": 4796491, "user_type": "registered", "profile_image": "https://www.gravatar.com/avatar/93d636cdebb342360df3bc9350a7be11?s=128&d=identicon&r=PG&f=1", "display_name": "sceee", "link": "https://stackoverflow.com/users/4796491/sceee"}, "edited": false, "score": 1, "creation_date": 1597996623, "post_id": 43611520, "comment_id": 112319780, "body": "As it&#39;s a little bit hidden in the answer, this is how to pass a typed function with return type as parameter in another function: <code>int outerFn(bool Function(String, bool) innerFn) { final result = innerFn(&quot;123&quot;, true); }</code>"}], "tags": [], "owner": {"reputation": 35316, "user_id": 2156621, "user_type": "registered", "profile_image": "https://www.gravatar.com/avatar/83ed6aa5c7920063019e39f13f94c1b6?s=128&d=identicon&r=PG&f=1", "display_name": "lrn", "link": "https://stackoverflow.com/users/2156621/lrn"}, "is_accepted": true, "score": 103, "last_activity_date": 1616315684, "last_edit_date": 1616315684, "creation_date": 1493125482, "answer_id": 43611520, "question_id": 43334714, "link": "https://stackoverflow.com/questions/43334714/pass-a-typed-function-as-a-parameter-in-dart/43611520#43611520", "title": "Pass a typed function as a parameter in Dart", "body": "\n<p>Dart v1.23 added a new syntax for writing function types which also works in-line.</p>\n<pre class=\"lang-dart prettyprint-override\"><code>void doSomething(Function(int) f) {\n  f(123);\n}\n</code></pre>\n<p>It has the advantage over the function-parameter syntax that you can also use it for variables or anywhere else you want to write a type.</p>\n<pre class=\"lang-dart prettyprint-override\"><code>void doSomething(Function(int) f) {\n  Function(int) g = f;\n  g(123);\n}\n\nvar x = &lt;int Function(int)&gt;[];\n\nint Function(int) returnsAFunction() =&gt; (int x) =&gt; x + 1;\n</code></pre>\n"}, {"tags": [], "owner": {"reputation": 10521, "user_id": 1316462, "user_type": "registered", "profile_image": "https://www.gravatar.com/avatar/2de3149d5f602449f41083ca17a5ceab?s=128&d=identicon&r=PG&f=1", "display_name": "Jans", "link": "https://stackoverflow.com/users/1316462/jans"}, "is_accepted": false, "score": 6, "last_activity_date": 1549917114, "last_edit_date": 1549917114, "creation_date": 1549915166, "answer_id": 54638183, "question_id": 43334714, "link": "https://stackoverflow.com/questions/43334714/pass-a-typed-function-as-a-parameter-in-dart/54638183#54638183", "title": "Pass a typed function as a parameter in Dart", "body": "<p>For reference.</p>\n\n<pre><code>int execute(int func(int a, int b)) =&gt; func(4, 3);\n\nprint(execute((a, b) =&gt; a + b));\n</code></pre>\n"}], "owner": {"reputation": 7501, "user_id": 1454, "user_type": "registered", "accept_rate": 84, "profile_image": "https://www.gravatar.com/avatar/a0e3ce2508a262749c9fc3afd681f2d4?s=128&d=identicon&r=PG", "display_name": "Raibaz", "link": "https://stackoverflow.com/users/1454/raibaz"}, "delete_vote_count": 0, "reopen_vote_count": 0, "close_vote_count": 0, "is_answered": true, "view_count": 44883, "favorite_count": 6, "accepted_answer_id": 43611520, "answer_count": 5, "score": 63, "last_activity_date": 1616315684, "creation_date": 1491869263, "question_id": 43334714, "link": "https://stackoverflow.com/questions/43334714/pass-a-typed-function-as-a-parameter-in-dart", "title": "Pass a typed function as a parameter in Dart", "body": "<p>I know the <a href=\"https://api.dartlang.org/stable/1.22.1/dart-core/Function-class.html\" rel=\"noreferrer\" title=\"Function\">Function</a> class can be passed as a parameter to another function, like this:</p>\n\n<pre><code>void doSomething(Function f) {\n    f(123);\n}\n</code></pre>\n\n<p>But is there a way to constrain the arguments and the return type of the function parameter?</p>\n\n<p>For instance, in this case <code>f</code> is being invoked directly on an integer, but what if it was a function accepting a different type?</p>\n\n<p>I tried passing it as a <code>Function&lt;Integer&gt;</code>, but Function is not a parametric type.</p>\n\n<p>Is there any other way to specify the signature of the function being passed as a parameter?</p>\n"}, {"tags": ["json", "api", "server", "dart"], "answers": [{"comments": [{"owner": {"reputation": 4197, "user_id": 7190575, "user_type": "registered", "accept_rate": 77, "profile_image": "https://www.gravatar.com/avatar/63b85f6a33e1b032dabc877b7ff4af50?s=128&d=identicon&r=PG&f=1", "display_name": "OhMad", "link": "https://stackoverflow.com/users/7190575/ohmad"}, "edited": false, "score": 0, "creation_date": 1491819662, "post_id": 43320507, "comment_id": 73705295, "body": "Oh, didn&#39;t know I could use then whencalling my GetEntryDiscussionsFromDb from main... thank you :)"}, {"owner": {"reputation": 483716, "user_id": 217408, "user_type": "registered", "accept_rate": 97, "profile_image": "https://i.stack.imgur.com/IlnZm.jpg?s=128&g=1", "display_name": "G&#252;nter Z&#246;chbauer", "link": "https://stackoverflow.com/users/217408/g%c3%bcnter-z%c3%b6chbauer"}, "reply_to_user": {"reputation": 4197, "user_id": 7190575, "user_type": "registered", "accept_rate": 77, "profile_image": "https://www.gravatar.com/avatar/63b85f6a33e1b032dabc877b7ff4af50?s=128&d=identicon&r=PG&f=1", "display_name": "OhMad", "link": "https://stackoverflow.com/users/7190575/ohmad"}, "edited": false, "score": 0, "creation_date": 1491819807, "post_id": 43320507, "comment_id": 73705387, "body": "<code>then()</code> returns a <code>Future</code> and you can call <code>then</code> on that <code>Future</code> again."}], "tags": [], "owner": {"reputation": 483716, "user_id": 217408, "user_type": "registered", "accept_rate": 97, "profile_image": "https://i.stack.imgur.com/IlnZm.jpg?s=128&g=1", "display_name": "G&#252;nter Z&#246;chbauer", "link": "https://stackoverflow.com/users/217408/g%c3%bcnter-z%c3%b6chbauer"}, "is_accepted": true, "score": 2, "last_activity_date": 1491819264, "creation_date": 1491819264, "answer_id": 43320507, "question_id": 43320382, "link": "https://stackoverflow.com/questions/43320382/dart-httprequest-getstring-return-json/43320507#43320507", "title": "Dart - HttpRequest.getString() return JSON", "body": "<p>Not sure what you try to accomplish. What is <code>return getRawJson;</code> supposed to do? </p>\n\n<p><code>getRawJson</code> just returns a reference to the <code>getRawJson</code> method. When you use <code>getRawJson</code></p>\n\n<pre><code>print(getRawJson());\n</code></pre>\n\n<p>calls <code>getRawJson</code> without a parameter, but it expects <code>String response</code>. This is why you get the error message.</p>\n\n<p>You can't avoid using <code>then</code>. Alternatively you can use <code>async</code>/<code>await</code></p>\n\n<pre><code>GetEntryDiscussionsFromDb(){\n  var url = \"http://localhost:8082/discussionApi/v1/getAllDiscussions\";\n\n  getRawJson(String response){\n    return response;\n  }\n\n  return HttpRequest.getString(url).then(getRawJson);\n}\n</code></pre>\n\n<p>main</p>\n\n<pre><code>GetEntryDiscussionsFromDb()\n.then(print);\n</code></pre>\n\n<p>or</p>\n\n<pre><code>main() async {\n  ...\n  var json = await GetEntryDiscussionsFromDb();\n  print(json);\n}\n</code></pre>\n"}], "owner": {"reputation": 4197, "user_id": 7190575, "user_type": "registered", "accept_rate": 77, "profile_image": "https://www.gravatar.com/avatar/63b85f6a33e1b032dabc877b7ff4af50?s=128&d=identicon&r=PG&f=1", "display_name": "OhMad", "link": "https://stackoverflow.com/users/7190575/ohmad"}, "delete_vote_count": 0, "reopen_vote_count": 0, "close_vote_count": 0, "is_answered": true, "view_count": 387, "favorite_count": 0, "accepted_answer_id": 43320507, "answer_count": 1, "score": 2, "last_activity_date": 1491819264, "creation_date": 1491818960, "question_id": 43320382, "link": "https://stackoverflow.com/questions/43320382/dart-httprequest-getstring-return-json", "title": "Dart - HttpRequest.getString() return JSON", "body": "<p>I am trying to return the raw JSON from my server path (I use rpc for the API) with a Closure, because I want to keep it in the same function instead of using .then() and calling another one.</p>\n\n<p>This is my code:</p>\n\n<pre><code>GetEntryDiscussionsFromDb(){\n  var url = \"http://localhost:8082/discussionApi/v1/getAllDiscussions\";\n\n  getRawJson(String response){\n    return response;\n  }\n\n  HttpRequest.getString(url).then(getRawJson);\n  return getRawJson;\n}\n</code></pre>\n\n<p>then in my main function I do this:</p>\n\n<pre><code>var getRawJson = GetEntryDiscussionsFromDb();\nprint(getRawJson());\n</code></pre>\n\n<p>By doing so I get this error:</p>\n\n<pre><code>G.GetEntryDiscussionsFromDb(...).call$0 is not a function\n</code></pre>\n\n<p>Did I use Closures wrong? Is there maybe a way to return the actual raw Json inside of .then() instead of calling another function?</p>\n\n<p>Thanks in advance</p>\n"}, {"tags": ["html", "forms", "templates", "dart"], "answers": [{"comments": [{"owner": {"reputation": 4197, "user_id": 7190575, "user_type": "registered", "accept_rate": 77, "profile_image": "https://www.gravatar.com/avatar/63b85f6a33e1b032dabc877b7ff4af50?s=128&d=identicon&r=PG&f=1", "display_name": "OhMad", "link": "https://stackoverflow.com/users/7190575/ohmad"}, "edited": false, "score": 0, "creation_date": 1491598792, "post_id": 43286688, "comment_id": 73642141, "body": "Cool, exactly what I was looking for. Thanks"}, {"owner": {"reputation": 4197, "user_id": 7190575, "user_type": "registered", "accept_rate": 77, "profile_image": "https://www.gravatar.com/avatar/63b85f6a33e1b032dabc877b7ff4af50?s=128&d=identicon&r=PG&f=1", "display_name": "OhMad", "link": "https://stackoverflow.com/users/7190575/ohmad"}, "edited": false, "score": 0, "creation_date": 1491641546, "post_id": 43286688, "comment_id": 73651332, "body": "I have now sent a request from my client to my server. My server received it. Is there a special function for HttpRequest in the dart:io in order to get the data I sent with the dart:html HttpRequest from my client?"}, {"owner": {"reputation": 483716, "user_id": 217408, "user_type": "registered", "accept_rate": 97, "profile_image": "https://i.stack.imgur.com/IlnZm.jpg?s=128&g=1", "display_name": "G&#252;nter Z&#246;chbauer", "link": "https://stackoverflow.com/users/217408/g%c3%bcnter-z%c3%b6chbauer"}, "reply_to_user": {"reputation": 4197, "user_id": 7190575, "user_type": "registered", "accept_rate": 77, "profile_image": "https://www.gravatar.com/avatar/63b85f6a33e1b032dabc877b7ff4af50?s=128&d=identicon&r=PG&f=1", "display_name": "OhMad", "link": "https://stackoverflow.com/users/7190575/ohmad"}, "edited": false, "score": 0, "creation_date": 1491642010, "post_id": 43286688, "comment_id": 73651436, "body": "Some example code <code>import &#39;dart:convert&#39;; ... if (request.method == &#39;POST&#39;) {         final requestData = await request.transform(UTF8.decoder).join();         final json = JSON.decode(requestData) as Map&lt;String, dynamic&gt;;}</code>. Perhaps it&#39;s somewhat different if you use <code>FormData</code>. I never used that."}], "tags": [], "owner": {"reputation": 483716, "user_id": 217408, "user_type": "registered", "accept_rate": 97, "profile_image": "https://i.stack.imgur.com/IlnZm.jpg?s=128&g=1", "display_name": "G&#252;nter Z&#246;chbauer", "link": "https://stackoverflow.com/users/217408/g%c3%bcnter-z%c3%b6chbauer"}, "is_accepted": true, "score": 4, "last_activity_date": 1491597180, "last_edit_date": 1495540465, "creation_date": 1491597180, "answer_id": 43286688, "question_id": 43283611, "link": "https://stackoverflow.com/questions/43283611/angulardart-use-form-action/43286688#43286688", "title": "AngularDart - Use Form Action", "body": "<p>In Angular you would instead do the request in code, because <code>form action=\"...\"</code> would reload the application or even another page which usually is not what you want in a single page application (SPA): </p>\n\n<pre><code>&lt;form (ngSubmit)=\"onSubmit()\"\n</code></pre>\n\n\n\n<p>and then post the form in Dart code like shown in the question in <a href=\"https://stackoverflow.com/questions/20749740/dart-ajax-form-submit\">Dart: AJAX form submit</a></p>\n\n<p>I haven't done this myself in years and don't have a full example, but it should get you going.</p>\n"}], "owner": {"reputation": 4197, "user_id": 7190575, "user_type": "registered", "accept_rate": 77, "profile_image": "https://www.gravatar.com/avatar/63b85f6a33e1b032dabc877b7ff4af50?s=128&d=identicon&r=PG&f=1", "display_name": "OhMad", "link": "https://stackoverflow.com/users/7190575/ohmad"}, "delete_vote_count": 0, "reopen_vote_count": 0, "close_vote_count": 0, "is_answered": true, "view_count": 262, "favorite_count": 0, "accepted_answer_id": 43286688, "answer_count": 1, "score": 2, "last_activity_date": 1491597180, "creation_date": 1491584792, "question_id": 43283611, "link": "https://stackoverflow.com/questions/43283611/angulardart-use-form-action", "title": "AngularDart - Use Form Action", "body": "<p>I am trying to use a form action attribute in AngularDart to redirect to the specified url. In plain html I would do something like this:</p>\n\n<p><code></p>\n\n<pre><code>&lt;form action=\"http://localhost:8082\" method=\"GET\"&gt;\n   &lt;select name=\"q\"&gt;\n        &lt;option value=\"0\"&gt;0&lt;/option&gt;\n        &lt;option value=\"1\"&gt;1&lt;/option&gt;\n        &lt;option value=\"2\"&gt;2&lt;/option&gt;\n        &lt;option value=\"9\"&gt;9&lt;/option&gt;\n      &lt;/select&gt;\n   &lt;input type=\"Submit\" value=\"Guess\"&gt;\n&lt;/form&gt;\n</code></pre>\n\n<p></code></p>\n\n<p>How would I implement this functionality with AngularDart?</p>\n\n<p>Thanks in advance</p>\n"}, {"tags": ["angularjs", "polymer", "dart", "service-worker", "progressive-web-apps"], "answers": [{"tags": [], "owner": {"reputation": 1868, "user_id": 1416886, "user_type": "registered", "accept_rate": 100, "profile_image": "https://www.gravatar.com/avatar/b1816b2eac989b20642bb419e3b51605?s=128&d=identicon&r=PG", "display_name": "filiph", "link": "https://stackoverflow.com/users/1416886/filiph"}, "is_accepted": false, "score": 3, "last_activity_date": 1493424351, "creation_date": 1493424351, "answer_id": 43690452, "question_id": 43274976, "link": "https://stackoverflow.com/questions/43274976/angular-dart-with-polymer-and-service-worker-incompatibilty/43690452#43690452", "title": "Angular Dart with Polymer and Service-Worker incompatibilty", "body": "<p>This looks like an issue caused by incompatibility between <code>dart:js</code> (the old style, used by the original polymer package) and <code>package:js</code> (the new style, used by all new packages, including <code>package:service_worker</code>). </p>\n\n<p>You might want to have a look at the <a href=\"https://dart-polymer.com/polymer2/\" rel=\"nofollow noreferrer\">polymerize</a> project, which brings Polymer via the new-style interop. Then you'll have no conflict.</p>\n"}], "owner": {"reputation": 43, "user_id": 5841420, "user_type": "registered", "profile_image": "https://i.stack.imgur.com/kl24D.jpg?s=128&g=1", "display_name": "7tupel", "link": "https://stackoverflow.com/users/5841420/7tupel"}, "delete_vote_count": 0, "reopen_vote_count": 0, "close_vote_count": 0, "is_answered": true, "view_count": 197, "favorite_count": 0, "answer_count": 1, "score": 3, "last_activity_date": 1493424351, "creation_date": 1491558553, "question_id": 43274976, "link": "https://stackoverflow.com/questions/43274976/angular-dart-with-polymer-and-service-worker-incompatibilty", "title": "Angular Dart with Polymer and Service-Worker incompatibilty", "body": "<p>I'm currently trying to build a web app compatible with the Google Progressive Web Apps specs. To do this i use Angular with Dart and Polymer based Webcomponents instead of the Angular components. So far everything works as expected. To make the app offline capable utilizing the Service-Worker API i use the following dart lib: <a href=\"https://github.com/isoos/service_worker\" rel=\"nofollow noreferrer\">https://github.com/isoos/service_worker</a></p>\n\n<p>Using either Polymer or Service-Worker works fine but combining booth just exits with an error on app startup.</p>\n\n<p>This is my AppComponent startup routine:</p>\n\n<pre><code>// ... other imports\nimport 'package:service_worker/window.dart' as sw; // &lt;-- import alone causes the error\n\nFuture main() async {\n  await initPolymer();  // &lt;-- causes the error in combination with the import above\n  bootstrap(AppComponent);\n\n  if (sw.isNotSupported) {\n    print('ServiceWorkers are not supported.');\n    return;\n  }\n  //... initializing service worker\n}\n</code></pre>\n\n<p>The error occurs even if i'm not initializing the Service-Worker, importing the Service-Worker module is enough to cause the error.</p>\n\n<p>Building the app works without any errors.</p>\n\n<p>I'm new to Dart and the Polymer and Angular eco systems and the error message i get is not very helpful to me:</p>\n\n<pre><code>Uncaught Error: NoSuchMethodError: method not found: js_helper.dart:1742 'h' (J.Q(...).h is not a function)\n    at Object.J.H (http://127.0.0.1:8080/index.bootstrap.initialize.dart.js:9747:15)\n    at http://127.0.0.1:8080/index.bootstrap.initialize.dart.js:10559:1584\n    at Isolate.e.(anonymous function) (http://127.0.0.1:8080/index.bootstrap.initialize.dart.js:10608:15)\n    at Object.yK (http://127.0.0.1:8080/index.bootstrap.initialize.dart.js:9291:22)\n    at http://127.0.0.1:8080/index.bootstrap.initialize.dart.js:9282:10\n    at yM.a (http://127.0.0.1:8080/index.bootstrap.initialize.dart.js:2612:72)\n    at yM.dart.yM.$2 (http://127.0.0.1:8080/index.bootstrap.initialize.dart.js:2828:24)\n    at y9.dart.y9.$1 (http://127.0.0.1:8080/index.bootstrap.initialize.dart.js:2824:31)\n    at xM.bi (http://127.0.0.1:8080/index.bootstrap.initialize.dart.js:3767:40)\n    at xk.$0 (http://127.0.0.1:8080/index.bootstrap.initialize.dart.js:3167:16)\n</code></pre>\n\n<p>Can you give me a hint what could cause the error and how to fix it? I would very much like to use the Polymer components instead of the plain Angular components but i need the Service-Worker for offline caching support.</p>\n"}, {"tags": ["angular", "dart", "future"], "comments": [{"owner": {"reputation": 483716, "user_id": 217408, "user_type": "registered", "accept_rate": 97, "profile_image": "https://i.stack.imgur.com/IlnZm.jpg?s=128&g=1", "display_name": "G&#252;nter Z&#246;chbauer", "link": "https://stackoverflow.com/users/217408/g%c3%bcnter-z%c3%b6chbauer"}, "edited": false, "score": 0, "creation_date": 1491553395, "post_id": 43269983, "comment_id": 73614315, "body": "What code is at line 86? I think you need to post more code. Have you tried checking with DartAnalyzer? Why was WebStorm a disaster. I&#39;m using is since 1.5 years and it&#39;s usually working great."}, {"owner": {"reputation": 2939, "user_id": 652220, "user_type": "registered", "accept_rate": 57, "profile_image": "https://i.stack.imgur.com/B3Bm7.png?s=128&g=1", "display_name": "Argenti Apparatus", "link": "https://stackoverflow.com/users/652220/argenti-apparatus"}, "edited": false, "score": 2, "creation_date": 1491561306, "post_id": 43269983, "comment_id": 73619587, "body": "Have you remembered to add <code>import &#39;dart:async&#39;;</code> ? (The library that <code>Future</code> is in.)"}, {"owner": {"reputation": 481, "user_id": 457480, "user_type": "registered", "accept_rate": 17, "profile_image": "https://i.stack.imgur.com/JRkfw.jpg?s=128&g=1", "display_name": "rickb", "link": "https://stackoverflow.com/users/457480/rickb"}, "edited": false, "score": 0, "creation_date": 1491581682, "post_id": 43269983, "comment_id": 73633689, "body": "import &#39;dart:async&#39;; -- Bingo!  I figured it was something like that. I didn&#39;t see it in the tutorial -- it may have been factored out of core since the tutorial was written.  &#39;importing&#39; it in both files did the trick. I&#39;m still learning the packages..."}, {"owner": {"reputation": 481, "user_id": 457480, "user_type": "registered", "accept_rate": 17, "profile_image": "https://i.stack.imgur.com/JRkfw.jpg?s=128&g=1", "display_name": "rickb", "link": "https://stackoverflow.com/users/457480/rickb"}, "edited": false, "score": 0, "creation_date": 1491582144, "post_id": 43269983, "comment_id": 73633981, "body": "The biggest hassle with WebStorm is it doesn&#39;t seem to trigger builds on save -- I can&#39;t tell when the server is running and when it isn&#39;t (this is on OS X Sierra).  And, all of these IDE&#39;s try to do too much -- code dances around as I type, windows constantly pop up all the time as I type -- if I type a quote it adds the second one and then positions the cursor <i>after</i> the second quote (not helpful).  And, I can&#39;t figure out how to bring up the pub console -- it comes and goes on its own.  I imaging I could figure out settings and all, but that&#39;s another road block."}, {"owner": {"reputation": 481, "user_id": 457480, "user_type": "registered", "accept_rate": 17, "profile_image": "https://i.stack.imgur.com/JRkfw.jpg?s=128&g=1", "display_name": "rickb", "link": "https://stackoverflow.com/users/457480/rickb"}, "edited": false, "score": 0, "creation_date": 1491582240, "post_id": 43269983, "comment_id": 73634058, "body": "Anyway, better to understand how all the different pieces work in the beginning, I think, and that means CL."}, {"owner": {"reputation": 2939, "user_id": 652220, "user_type": "registered", "accept_rate": 57, "profile_image": "https://i.stack.imgur.com/B3Bm7.png?s=128&g=1", "display_name": "Argenti Apparatus", "link": "https://stackoverflow.com/users/652220/argenti-apparatus"}, "edited": false, "score": 0, "creation_date": 1491592048, "post_id": 43269983, "comment_id": 73638983, "body": "Sublime Text wit the Dart module works quite well, although there appears to be no ongoing development on that module so it will eventually break. I&#39;m also trying out Atom and its Dart support."}, {"owner": {"reputation": 483716, "user_id": 217408, "user_type": "registered", "accept_rate": 97, "profile_image": "https://i.stack.imgur.com/IlnZm.jpg?s=128&g=1", "display_name": "G&#252;nter Z&#246;chbauer", "link": "https://stackoverflow.com/users/217408/g%c3%bcnter-z%c3%b6chbauer"}, "edited": false, "score": 0, "creation_date": 1491598232, "post_id": 43269983, "comment_id": 73641907, "body": "Running dartanalyzer over your source would immediately show you such errors."}, {"owner": {"reputation": 12020, "user_id": 3046255, "user_type": "registered", "accept_rate": 70, "profile_image": "https://www.gravatar.com/avatar/c735441a8f71994ab500ce5e599b7fda?s=128&d=identicon&r=PG", "display_name": "Patrice Chalin", "link": "https://stackoverflow.com/users/3046255/patrice-chalin"}, "edited": false, "score": 0, "creation_date": 1493424759, "post_id": 43269983, "comment_id": 74427187, "body": "@rickb - sorry about the troubles you had. I&#39;ve created an issue so that this gets fixed: <a href=\"https://github.com/dart-lang/site-webdev/issues/585\" rel=\"nofollow noreferrer\">github.com/dart-lang/site-webdev/issues/585</a>"}], "answers": [{"tags": [], "owner": {"reputation": 2939, "user_id": 652220, "user_type": "registered", "accept_rate": 57, "profile_image": "https://i.stack.imgur.com/B3Bm7.png?s=128&g=1", "display_name": "Argenti Apparatus", "link": "https://stackoverflow.com/users/652220/argenti-apparatus"}, "is_accepted": true, "score": 2, "last_activity_date": 1491589414, "creation_date": 1491589414, "answer_id": 43284783, "question_id": 43269983, "link": "https://stackoverflow.com/questions/43269983/angular-dart-tutorial-section-4-future-not-resolved/43284783#43284783", "title": "Angular Dart tutorial section 4 - &#39;Future not resolved&#39;", "body": "<p>Remember to add <code>import 'dart:async';</code> ? (The library that <code>Future</code> is in.) </p>\n"}], "owner": {"reputation": 481, "user_id": 457480, "user_type": "registered", "accept_rate": 17, "profile_image": "https://i.stack.imgur.com/JRkfw.jpg?s=128&g=1", "display_name": "rickb", "link": "https://stackoverflow.com/users/457480/rickb"}, "delete_vote_count": 0, "reopen_vote_count": 0, "close_vote_count": 0, "is_answered": true, "view_count": 119, "favorite_count": 0, "accepted_answer_id": 43284783, "answer_count": 1, "score": 1, "last_activity_date": 1491589414, "creation_date": 1491541191, "question_id": 43269983, "link": "https://stackoverflow.com/questions/43269983/angular-dart-tutorial-section-4-future-not-resolved", "title": "Angular Dart tutorial section 4 - &#39;Future not resolved&#39;", "body": "<p>Total newbie to Dart and Angular. Long-time SW developer with a lot of experience with multiple languages and platforms.</p>\n\n<p>I'm working through the 'Tour of Heroes' tutorial, but am stumped in <a href=\"https://webdev.dartlang.org/angular/tutorial/toh-pt4\" rel=\"nofollow noreferrer\">section 4.</a>, under the heading 'The Hero Service returns a Future'.</p>\n\n<p>Thus far, I've gotten things to work pretty well, but now when I try to mod the code to return a future (per the tutorial), I get an error.</p>\n\n<p>In hero_service.dart, this:</p>\n\n<pre><code>Future&lt;List&lt;Hero&gt;&gt; getHeroes() async =&gt; mockHeroes;\n</code></pre>\n\n<p>and in app_component.dart, this:</p>\n\n<pre><code>  Future&lt;Null&gt; getHeroes() async {\n     heroes = await _heroService.getHeroes();\n     }\n</code></pre>\n\n<p>But, I'm getting this error:</p>\n\n<pre><code>EXCEPTION: 'package:Tour_Of_Heroes/app_component.dart': malformed type: line \n            86 pos 3: cannot resolve class 'Future' from 'AppComponent'\n            Future&lt;Null&gt; getHeroes() async {\n            ^\n</code></pre>\n\n<p>I've backed it out and re-entered everything to make sure I've entered everything correctly and still getting the error.</p>\n\n<p>I'm wondering if something in the core was refactored and I need to import something else or clean the build (not sure how to do that...) to get it fresh or what.</p>\n\n<p>(BTW: Doing everything from the CL and VIM.  Webstorm was a disaster...)</p>\n"}, {"tags": ["html", "dart", "angular-dart"], "answers": [{"tags": [], "owner": {"reputation": 7501, "user_id": 1454, "user_type": "registered", "accept_rate": 84, "profile_image": "https://www.gravatar.com/avatar/a0e3ce2508a262749c9fc3afd681f2d4?s=128&d=identicon&r=PG", "display_name": "Raibaz", "link": "https://stackoverflow.com/users/1454/raibaz"}, "is_accepted": true, "score": 5, "last_activity_date": 1491513687, "creation_date": 1491513687, "answer_id": 43265975, "question_id": 43265694, "link": "https://stackoverflow.com/questions/43265694/creating-a-table-with-nested-lists-in-angulardart/43265975#43265975", "title": "Creating a table with nested lists in Angulardart", "body": "<p>Turns out the issue was in the grid initialization: the correct initialization code to have it filled with lists of zeroes is</p>\n\n<pre><code>cells.fillRange(0, cells.length, new List.filled(GRID_SIZE, 0));\n</code></pre>\n\n<p>The initialization code in the question only filled the main list with <code>GRID_SIZE</code> nulls.</p>\n"}, {"tags": [], "owner": {"reputation": 1914, "user_id": 2033675, "user_type": "registered", "accept_rate": 75, "profile_image": "https://i.stack.imgur.com/8BDsq.jpg?s=128&g=1", "display_name": "Zied Hamdi", "link": "https://stackoverflow.com/users/2033675/zied-hamdi"}, "is_accepted": false, "score": 0, "last_activity_date": 1491553175, "creation_date": 1491553175, "answer_id": 43273156, "question_id": 43265694, "link": "https://stackoverflow.com/questions/43265694/creating-a-table-with-nested-lists-in-angulardart/43273156#43273156", "title": "Creating a table with nested lists in Angulardart", "body": "<p>When you call this line:</p>\n\n<pre><code>cells.forEach((x) =&gt; x = new List(GRID_SIZE));\n</code></pre>\n\n<p>You are actually replacing x with a new value : you are not intervening inside x, but you created a new one.</p>\n\n<pre><code>List&lt;String&gt; myList = ['my', 'original', 'list'];\n\nvoid yourForLoopFunctionSimulation( List&lt;String&gt; x ) {\n  x = new List.filled(GRID_SIZE, 0);\n  //you can work with the new x value here, but it won't change the argument that was passed to you\n}\n\n//if you run \nyourForLoopFunctionSimulation( myList );\nprint( myList ); // result : ['my', 'original', 'list'];\n</code></pre>\n"}], "owner": {"reputation": 7501, "user_id": 1454, "user_type": "registered", "accept_rate": 84, "profile_image": "https://www.gravatar.com/avatar/a0e3ce2508a262749c9fc3afd681f2d4?s=128&d=identicon&r=PG", "display_name": "Raibaz", "link": "https://stackoverflow.com/users/1454/raibaz"}, "delete_vote_count": 0, "reopen_vote_count": 0, "close_vote_count": 0, "is_answered": true, "view_count": 290, "favorite_count": 0, "accepted_answer_id": 43265975, "answer_count": 2, "score": 1, "last_activity_date": 1491553175, "creation_date": 1491512511, "question_id": 43265694, "link": "https://stackoverflow.com/questions/43265694/creating-a-table-with-nested-lists-in-angulardart", "title": "Creating a table with nested lists in Angulardart", "body": "<p>I'm trying to build a table representing a <code>List&lt;List&lt;int&gt;&gt;</code> in Angulardart.</p>\n\n<p>This is the content of my template file:</p>\n\n<pre><code>&lt;table&gt;\n    &lt;tbody&gt;\n        &lt;tr *ngFor=\"#row of cells\"&gt;\n            &lt;td *ngFor=\"#cell of row\"&gt;\n                &lt;input type=\"number\" #cell (keyup)=\"0\"/&gt;\n            &lt;/td&gt;\n        &lt;/tr&gt;\n    &lt;/tbody&gt;\n&lt;/table&gt;\n</code></pre>\n\n<p>And the list is initialized like this:</p>\n\n<pre><code>class Grid {\n    const GRID_SIZE = 9;\n    List&lt;List&lt;int&gt;&gt; cells = new List(GRID_SIZE);\n\n    Grid() {\n        cells.forEach((x) =&gt; x = new List(GRID_SIZE));\n    }\n}\n</code></pre>\n\n<p>However, in the rendered HTML I only see 9 <code>&lt;tr&gt;</code> empty tags, with no <code>&lt;td&gt;</code>s inside.</p>\n\n<p>What am I missing?</p>\n"}, {"tags": ["angular", "dart", "angular-dart", "angular-template"], "answers": [{"tags": [], "owner": {"reputation": 483716, "user_id": 217408, "user_type": "registered", "accept_rate": 97, "profile_image": "https://i.stack.imgur.com/IlnZm.jpg?s=128&g=1", "display_name": "G&#252;nter Z&#246;chbauer", "link": "https://stackoverflow.com/users/217408/g%c3%bcnter-z%c3%b6chbauer"}, "is_accepted": false, "score": 4, "last_activity_date": 1491508431, "last_edit_date": 1491508431, "creation_date": 1491497494, "answer_id": 43261330, "question_id": 43260815, "link": "https://stackoverflow.com/questions/43260815/angular-2-dart-inline-conditionals-is-the-second-condition-evaluated-if-the/43261330#43261330", "title": "Angular 2 (+Dart) inline conditionals: Is the second condition evaluated if the first is false? How to solve?", "body": "<p>No, with <code>&amp;&amp;</code> short-circuit evaluation stops evaluating the 2nd part when the first is <code>false</code> - the same as in normal Dart code.</p>\n"}, {"tags": [], "owner": {"reputation": 2071, "user_id": 7117017, "user_type": "registered", "profile_image": "https://lh5.googleusercontent.com/-jZmAx2-S2uw/AAAAAAAAAAI/AAAAAAAAHlg/0D73i8yexr0/photo.jpg?sz=128", "display_name": "Harry Terkelsen", "link": "https://stackoverflow.com/users/7117017/harry-terkelsen"}, "is_accepted": true, "score": 4, "last_activity_date": 1491497518, "creation_date": 1491497518, "answer_id": 43261335, "question_id": 43260815, "link": "https://stackoverflow.com/questions/43260815/angular-2-dart-inline-conditionals-is-the-second-condition-evaluated-if-the/43261335#43261335", "title": "Angular 2 (+Dart) inline conditionals: Is the second condition evaluated if the first is false? How to solve?", "body": "<p>Angular will write this into the generated template file:</p>\n\n<p><code>_NgIf_0_5.ngIf = ((ctx.selectedOffer != null) &amp;&amp; !ctx.selectedOffer.isBotenOffer);\n</code></p>\n\n<p>So it shouldn't evaluate <code>selectedOffer.isBotenOffer</code> if <code>selectedOffer</code> is <code>null</code>. However, you may be hitting a bug that was just fixed in dart2js: <a href=\"https://github.com/dart-lang/sdk/commit/fe7baee84828e109a49920c2572f3917e5ff8ca5\" rel=\"nofollow noreferrer\">https://github.com/dart-lang/sdk/commit/fe7baee84828e109a49920c2572f3917e5ff8ca5</a></p>\n\n<p>You might hit this issue if you are setting <code>selectedOffer</code> in your component's constructor, but doing an early return in the constructor.</p>\n"}], "owner": {"reputation": 11950, "user_id": 576746, "user_type": "registered", "accept_rate": 83, "profile_image": "https://www.gravatar.com/avatar/fd655b00d23f25a744dbd630b7fdd09d?s=128&d=identicon&r=PG", "display_name": "Blackbam", "link": "https://stackoverflow.com/users/576746/blackbam"}, "delete_vote_count": 0, "reopen_vote_count": 0, "close_vote_count": 0, "is_answered": true, "view_count": 256, "favorite_count": 0, "accepted_answer_id": 43261335, "answer_count": 2, "score": 2, "last_activity_date": 1491508780, "creation_date": 1491496079, "last_edit_date": 1491508780, "question_id": 43260815, "link": "https://stackoverflow.com/questions/43260815/angular-2-dart-inline-conditionals-is-the-second-condition-evaluated-if-the", "title": "Angular 2 (+Dart) inline conditionals: Is the second condition evaluated if the first is false? How to solve?", "body": "<p>This is the code in my <code>component.html</code> (Angular Dart template):</p>\n\n<pre><code>&lt;div *ngIf=\"selectedOffer!=null &amp;&amp; !selectedOffer.isBotenOffer\"&gt;...&lt;/div&gt;\n</code></pre>\n\n<p>This is the exception I get:</p>\n\n<blockquote>\n  <p>EXCEPTION: NoSuchMethodError: The getter 'isBotenOffer' was called on\n  null. Receiver: null Tried calling: isBotenOffer</p>\n</blockquote>\n\n<p><code>selectedOffer</code> my be <code>null</code> sometimes. But why is the second statement evaluated if the first is false? And how can I around this best?</p>\n"}]